pylivestream/__init__.py
pylivestream/api.py
pylivestream/base.py
pylivestream/camera.py
pylivestream/ffmpeg.py
pylivestream/fglob.py
pylivestream/loopfile.py
pylivestream/microphone.py
pylivestream/screen.py
pylivestream/screen2disk.py
pylivestream/stream.py
pylivestream/utils.py
pylivestream/data/__init__.py
pylivestream/data/bunny.avi
pylivestream/data/check4k.png
pylivestream/data/logo.png
pylivestream/data/orch.ogg
pylivestream/data/orch_short.ogg
pylivestream/data/pylivestream.json
pylivestream/tests/test_class.py
pylivestream/tests/test_disk.py
pylivestream/tests/test_filein.py
pylivestream/tests/test_microphone.py
pylivestream/tests/test_screen.py
pylivestream/tests/test_webcam.py
pylivestream-2.1.1.dist-info/LICENSE.txt
pylivestream-2.1.1.dist-info/METADATA
pylivestream-2.1.1.dist-info/WHEEL
pylivestream-2.1.1.dist-info/top_level.txt
pylivestream-2.1.1.dist-info/RECORD
