Metadata-Version: 2.1
Name: pylivestream
Version: 2.1.1
Summary: Livestream using FFmpeg to YouTube Live, X, Facebook Live, Twitch, and more
Keywords: youtube,ffmpeg,twitch,X,facebook live,restream.io
Classifier: Development Status :: 5 - Production/Stable
Classifier: Environment :: Console
Classifier: Intended Audience :: End Users/Desktop
Classifier: License :: OSI Approved :: Apache Software License
Classifier: Operating System :: OS Independent
Classifier: Programming Language :: Python :: 3
Classifier: Topic :: Multimedia :: Graphics :: Capture :: Screen Capture
Classifier: Topic :: Multimedia :: Sound/Audio :: Capture/Recording
Classifier: Topic :: Multimedia :: Video :: Capture
Requires-Python: >=3.9
License-File: LICENSE.txt
Provides-Extra: tests
Requires-Dist: pytest; extra == "tests"
Requires-Dist: pytest-timeout; extra == "tests"
Provides-Extra: lint
Requires-Dist: flake8; extra == "lint"
Requires-Dist: flake8-bugbear; extra == "lint"
Requires-Dist: flake8-builtins; extra == "lint"
Requires-Dist: flake8-blind-except; extra == "lint"
Requires-Dist: mypy; extra == "lint"
Provides-Extra: captions
Requires-Dist: tinytag; extra == "captions"
